pyARdotless/__init__.py
pyARdotless/src/__init__.py
pyARdotless/src/arwiki.wordlist
pyARdotless/src/predictdots.py
pyARdotless/src/roots.txt
pyARdotless/src/utils.py
pyARdotless/test/__init__.py
pyARdotless-0.0.10.dist-info/LICENSE
pyARdotless-0.0.10.dist-info/METADATA
pyARdotless-0.0.10.dist-info/WHEEL
pyARdotless-0.0.10.dist-info/top_level.txt
pyARdotless-0.0.10.dist-info/RECORD
